{
  "name": "item-09",
  "elements": [
    {
      "type": "ellipse",
      "version": 1888,
      "versionNonce": 1788397296,
      "isDeleted": false,
      "id": "NJ7Bkz3XLWIQyu1T1lRBE",
      "fillStyle": "cross-hatch",
      "strokeWidth": 1,
      "strokeStyle": "solid",
      "roughness": 1,
      "opacity": 100,
      "angle": 0,
      "x": 891.0375289522568,
      "y": 594.2196824268583,
      "strokeColor": "#000000",
      "backgroundColor": "#000000",
      "width": 12.229002095673158,
      "height": 10.681727608499656,
      "seed": 1143689744,
      "groupIds": [
        "u2YeWM_1DGS08E8xP1afa"
      ],
      "strokeSharpness": "round",
      "boundElementIds": []
    },
    {
      "type": "ellipse",
      "version": 1955,
      "versionNonce": 1030709264,
      "isDeleted": false,
      "id": "TO8u7Lw_xZu5q1FKr1tGW",
      "fillStyle": "cross-hatch",
      "strokeWidth": 1,
      "strokeStyle": "solid",
      "roughness": 1,
      "opacity": 100,
      "angle": 0,
      "x": 932.5697566144937,
      "y": 580.4986577370471,
      "strokeColor": "#000000",
      "backgroundColor": "#000000",
      "width": 12.229002095673158,
      "height": 10.681727608499656,
      "seed": 1685493488,
      "groupIds": [
        "u2YeWM_1DGS08E8xP1afa"
      ],
      "strokeSharpness": "round",
      "boundElementIds": []
    },
    {
      "type": "ellipse",
      "version": 1937,
      "versionNonce": 465725680,
      "isDeleted": false,
      "id": "sfJTSXelJ_3dWyWA327aD",
      "fillStyle": "cross-hatch",
      "strokeWidth": 1,
      "strokeStyle": "solid",
      "roughness": 1,
      "opacity": 100,
      "angle": 0,
      "x": 958.0316884020391,
      "y": 554.2302326768463,
      "strokeColor": "#000000",
      "backgroundColor": "#000000",
      "width": 12.229002095673158,
      "height": 10.681727608499656,
      "seed": 890671120,
      "groupIds": [
        "u2YeWM_1DGS08E8xP1afa"
      ],
      "strokeSharpness": "round",
      "boundElementIds": []
    },
    {
      "type": "ellipse",
      "version": 1937,
      "versionNonce": 1185472016,
      "isDeleted": false,
      "id": "Sxe6dI9SdlUGfQSKOZ_k5",
      "fillStyle": "cross-hatch",
      "strokeWidth": 1,
      "strokeStyle": "solid",
      "roughness": 1,
      "opacity": 100,
      "angle": 0,
      "x": 966.9269663280473,
      "y": 519.4526327546257,
      "strokeColor": "#000000",
      "backgroundColor": "#000000",
      "width": 12.229002095673158,
      "height": 10.681727608499656,
      "seed": 963000560,
      "groupIds": [
        "u2YeWM_1DGS08E8xP1afa"
      ],
      "strokeSharpness": "round",
      "boundElementIds": []
    },
    {
      "type": "ellipse",
      "version": 1925,
      "versionNonce": 2070399728,
      "isDeleted": false,
      "id": "OV2uVoUHTnWGguSD7KVe-",
      "fillStyle": "cross-hatch",
      "strokeWidth": 1,
      "strokeStyle": "solid",
      "roughness": 1,
      "opacity": 100,
      "angle": 0,
      "x": 957.1461856220668,
      "y": 480.90940989942095,
      "strokeColor": "#000000",
      "backgroundColor": "#000000",
      "width": 12.229002095673158,
      "height": 10.681727608499656,
      "seed": 568987152,
      "groupIds": [
        "u2YeWM_1DGS08E8xP1afa"
      ],
      "strokeSharpness": "round",
      "boundElementIds": []
    },
    {
      "type": "ellipse",
      "version": 1913,
      "versionNonce": 671259664,
      "isDeleted": false,
      "id": "hhDrMX1EyrQGVznte3PQ3",
      "fillStyle": "cross-hatch",
      "strokeWidth": 1,
      "strokeStyle": "solid",
      "roughness": 1,
      "opacity": 100,
      "angle": 0,
      "x": 931.0208721222749,
      "y": 450.8813248879173,
      "strokeColor": "#000000",
      "backgroundColor": "#000000",
      "width": 12.229002095673158,
      "height": 10.681727608499656,
      "seed": 1410439920,
      "groupIds": [
        "u2YeWM_1DGS08E8xP1afa"
      ],
      "strokeSharpness": "round",
      "boundElementIds": []
    },
    {
      "type": "ellipse",
      "version": 1920,
      "versionNonce": 1141959920,
      "isDeleted": false,
      "id": "P8aq-Q0UuqMBDfsLzQAaj",
      "fillStyle": "cross-hatch",
      "strokeWidth": 1,
      "strokeStyle": "solid",
      "roughness": 1,
      "opacity": 100,
      "angle": 0,
      "x": 890.5113560570118,
      "y": 439.8155216292029,
      "strokeColor": "#000000",
      "backgroundColor": "#000000",
      "width": 12.229002095673158,
      "height": 10.681727608499656,
      "seed": 1671285776,
      "groupIds": [
        "u2YeWM_1DGS08E8xP1afa"
      ],
      "strokeSharpness": "round",
      "boundElementIds": []
    },
    {
      "type": "ellipse",
      "version": 1922,
      "versionNonce": 1937021456,
      "isDeleted": false,
      "id": "3hT4fejv9c83JEM8Ez2Mj",
      "fillStyle": "cross-hatch",
      "strokeWidth": 1,
      "strokeStyle": "solid",
      "roughness": 1,
      "opacity": 100,
      "angle": 0,
      "x": 851.0408895500562,
      "y": 449.1595139268772,
      "strokeColor": "#000000",
      "backgroundColor": "#000000",
      "width": 12.229002095673158,
      "height": 10.681727608499656,
      "seed": 117488880,
      "groupIds": [
        "u2YeWM_1DGS08E8xP1afa"
      ],
      "strokeSharpness": "round",
      "boundElementIds": []
    },
    {
      "type": "ellipse",
      "version": 1919,
      "versionNonce": 524668656,
      "isDeleted": false,
      "id": "1VMRlUpLSVJ5l3TmbM1JR",
      "fillStyle": "cross-hatch",
      "strokeWidth": 1,
      "strokeStyle": "solid",
      "roughness": 1,
      "opacity": 100,
      "angle": 0,
      "x": 823.0998481277012,
      "y": 475.000095051306,
      "strokeColor": "#000000",
      "backgroundColor": "#000000",
      "width": 12.229002095673158,
      "height": 10.681727608499656,
      "seed": 1948895760,
      "groupIds": [
        "u2YeWM_1DGS08E8xP1afa"
      ],
      "strokeSharpness": "round",
      "boundElementIds": []
    },
    {
      "type": "ellipse",
      "version": 1911,
      "versionNonce": 1006032912,
      "isDeleted": false,
      "id": "RjxAVzride8K8mmsEyhLc",
      "fillStyle": "cross-hatch",
      "strokeWidth": 1,
      "strokeStyle": "solid",
      "roughness": 1,
      "opacity": 100,
      "angle": 0,
      "x": 811.904350017359,
      "y": 515.2576751404463,
      "strokeColor": "#000000",
      "backgroundColor": "#000000",
      "width": 12.229002095673158,
      "height": 10.681727608499656,
      "seed": 331063024,
      "groupIds": [
        "u2YeWM_1DGS08E8xP1afa"
      ],
      "strokeSharpness": "round",
      "boundElementIds": []
    },
    {
      "type": "ellipse",
      "version": 1946,
      "versionNonce": 1166962928,
      "isDeleted": false,
      "id": "Vep7-vF5n7vm7MZcAmIO3",
      "fillStyle": "cross-hatch",
      "strokeWidth": 1,
      "strokeStyle": "solid",
      "roughness": 1,
      "opacity": 100,
      "angle": 0,
      "x": 822.7420692267004,
      "y": 556.5379065882703,
      "strokeColor": "#000000",
      "backgroundColor": "#000000",
      "width": 12.229002095673158,
      "height": 10.681727608499656,
      "seed": 1317406736,
      "groupIds": [
        "u2YeWM_1DGS08E8xP1afa"
      ],
      "strokeSharpness": "round",
      "boundElementIds": []
    },
    {
      "type": "ellipse",
      "version": 1917,
      "versionNonce": 1971410448,
      "isDeleted": false,
      "id": "1U5dSiyenUdZSKwXZGa7I",
      "fillStyle": "cross-hatch",
      "strokeWidth": 1,
      "strokeStyle": "solid",
      "roughness": 1,
      "opacity": 100,
      "angle": 0,
      "x": 850.5683232516652,
      "y": 582.8704337015652,
      "strokeColor": "#000000",
      "backgroundColor": "#000000",
      "width": 12.229002095673158,
      "height": 10.681727608499656,
      "seed": 1254768880,
      "groupIds": [
        "u2YeWM_1DGS08E8xP1afa"
      ],
      "strokeSharpness": "round",
      "boundElementIds": []
    },
    {
      "type": "ellipse",
      "version": 2167,
      "versionNonce": 510841584,
      "isDeleted": false,
      "id": "yd8zb3z1tmm9yFh_qpCQB",
      "fillStyle": "cross-hatch",
      "strokeWidth": 1,
      "strokeStyle": "solid",
      "roughness": 1,
      "opacity": 100,
      "angle": 0,
      "x": 995.7987433824072,
      "y": 520.2433430328392,
      "strokeColor": "#000000",
      "backgroundColor": "#000000",
      "width": 15.175078643650115,
      "height": 13.513925750184024,
      "seed": 1319798288,
      "groupIds": [
        "u2YeWM_1DGS08E8xP1afa"
      ],
      "strokeSharpness": "round",
      "boundElementIds": []
    },
    {
      "type": "ellipse",
      "version": 2231,
      "versionNonce": 1426854928,
      "isDeleted": false,
      "id": "rqAApP4uePFXozK0PSKoG",
      "fillStyle": "cross-hatch",
      "strokeWidth": 1,
      "strokeStyle": "solid",
      "roughness": 1,
      "opacity": 100,
      "angle": 0,
      "x": 981.3224781973021,
      "y": 568.1344850273165,
      "strokeColor": "#000000",
      "backgroundColor": "#000000",
      "width": 15.175078643650115,
      "height": 13.513925750184024,
      "seed": 733258480,
      "groupIds": [
        "u2YeWM_1DGS08E8xP1afa"
      ],
      "strokeSharpness": "round",
      "boundElementIds": []
    },
    {
      "type": "ellipse",
      "version": 2153,
      "versionNonce": 1618670832,
      "isDeleted": false,
      "id": "xrHAr8exjppuBQya9G0VK",
      "fillStyle": "cross-hatch",
      "strokeWidth": 1,
      "strokeStyle": "solid",
      "roughness": 1,
      "opacity": 100,
      "angle": 0,
      "x": 945.0901652618667,
      "y": 603.213251884185,
      "strokeColor": "#000000",
      "backgroundColor": "#000000",
      "width": 15.175078643650115,
      "height": 13.513925750184024,
      "seed": 294601744,
      "groupIds": [
        "u2YeWM_1DGS08E8xP1afa"
      ],
      "strokeSharpness": "round",
      "boundElementIds": []
    },
    {
      "type": "ellipse",
      "version": 2109,
      "versionNonce": 814682640,
      "isDeleted": false,
      "id": "aEIgbaqyAzeY8I3BPJsa5",
      "fillStyle": "cross-hatch",
      "strokeWidth": 1,
      "strokeStyle": "solid",
      "roughness": 1,
      "opacity": 100,
      "angle": 0,
      "x": 888.1741595686932,
      "y": 616.3936229828635,
      "strokeColor": "#000000",
      "backgroundColor": "#000000",
      "width": 15.175078643650115,
      "height": 13.513925750184024,
      "seed": 84067568,
      "groupIds": [
        "u2YeWM_1DGS08E8xP1afa"
      ],
      "strokeSharpness": "round",
      "boundElementIds": []
    },
    {
      "type": "ellipse",
      "version": 2189,
      "versionNonce": 825153264,
      "isDeleted": false,
      "id": "scWtsxFNUdU2U6_UTjSHc",
      "fillStyle": "cross-hatch",
      "strokeWidth": 1,
      "strokeStyle": "solid",
      "roughness": 1,
      "opacity": 100,
      "angle": 0,
      "x": 833.1455830168862,
      "y": 603.310259415475,
      "strokeColor": "#000000",
      "backgroundColor": "#000000",
      "width": 15.175078643650115,
      "height": 13.513925750184024,
      "seed": 1428963856,
      "groupIds": [
        "u2YeWM_1DGS08E8xP1afa"
      ],
      "strokeSharpness": "round",
      "boundElementIds": []
    },
    {
      "type": "ellipse",
      "version": 2154,
      "versionNonce": 1593987088,
      "isDeleted": false,
      "id": "HwOc5f7mGKo275U37mWhQ",
      "fillStyle": "cross-hatch",
      "strokeWidth": 1,
      "strokeStyle": "solid",
      "roughness": 1,
      "opacity": 100,
      "angle": 0,
      "x": 795.3105369558581,
      "y": 563.1196174316892,
      "strokeColor": "#000000",
      "backgroundColor": "#000000",
      "width": 15.175078643650115,
      "height": 13.513925750184024,
      "seed": 339519216,
      "groupIds": [
        "u2YeWM_1DGS08E8xP1afa"
      ],
      "strokeSharpness": "round",
      "boundElementIds": []
    },
    {
      "type": "ellipse",
      "version": 2100,
      "versionNonce": 1159100656,
      "isDeleted": false,
      "id": "oRaDk32NqlCoaTX4br-yj",
      "fillStyle": "cross-hatch",
      "strokeWidth": 1,
      "strokeStyle": "solid",
      "roughness": 1,
      "opacity": 100,
      "angle": 0,
      "x": 779.7134130125143,
      "y": 512.1611394751319,
      "strokeColor": "#000000",
      "backgroundColor": "#000000",
      "width": 15.175078643650115,
      "height": 13.513925750184024,
      "seed": 1484357648,
      "groupIds": [
        "u2YeWM_1DGS08E8xP1afa"
      ],
      "strokeSharpness": "round",
      "boundElementIds": []
    },
    {
      "type": "ellipse",
      "version": 2136,
      "versionNonce": 408800784,
      "isDeleted": false,
      "id": "Y6s7bt13IKhsYxW9k8hG3",
      "fillStyle": "cross-hatch",
      "strokeWidth": 1,
      "strokeStyle": "solid",
      "roughness": 1,
      "opacity": 100,
      "angle": 0,
      "x": 795.7555062841399,
      "y": 459.62101698672785,
      "strokeColor": "#000000",
      "backgroundColor": "#000000",
      "width": 15.175078643650115,
      "height": 13.513925750184024,
      "seed": 636111088,
      "groupIds": [
        "u2YeWM_1DGS08E8xP1afa"
      ],
      "strokeSharpness": "round",
      "boundElementIds": []
    },
    {
      "type": "ellipse",
      "version": 2119,
      "versionNonce": 2142886640,
      "isDeleted": false,
      "id": "0e0kRo7APXx4XZcZB0kja",
      "fillStyle": "cross-hatch",
      "strokeWidth": 1,
      "strokeStyle": "solid",
      "roughness": 1,
      "opacity": 100,
      "angle": 0,
      "x": 839.027191815958,
      "y": 423.6480937545238,
      "strokeColor": "#000000",
      "backgroundColor": "#000000",
      "width": 15.175078643650115,
      "height": 13.513925750184024,
      "seed": 997129744,
      "groupIds": [
        "u2YeWM_1DGS08E8xP1afa"
      ],
      "strokeSharpness": "round",
      "boundElementIds": []
    },
    {
      "type": "ellipse",
      "version": 2128,
      "versionNonce": 1436126224,
      "isDeleted": false,
      "id": "AaeF6gtguQiRJDQjU1KoA",
      "fillStyle": "cross-hatch",
      "strokeWidth": 1,
      "strokeStyle": "solid",
      "roughness": 1,
      "opacity": 100,
      "angle": 0,
      "x": 892.6322882891399,
      "y": 412.6967870160526,
      "strokeColor": "#000000",
      "backgroundColor": "#000000",
      "width": 15.175078643650115,
      "height": 13.513925750184024,
      "seed": 898870000,
      "groupIds": [
        "u2YeWM_1DGS08E8xP1afa"
      ],
      "strokeSharpness": "round",
      "boundElementIds": []
    },
    {
      "type": "ellipse",
      "version": 2130,
      "versionNonce": 329317616,
      "isDeleted": false,
      "id": "14_brSZ1tZbBMfqkt7FWT",
      "fillStyle": "cross-hatch",
      "strokeWidth": 1,
      "strokeStyle": "solid",
      "roughness": 1,
      "opacity": 100,
      "angle": 0,
      "x": 948.5950895444338,
      "y": 432.6023106641198,
      "strokeColor": "#000000",
      "backgroundColor": "#000000",
      "width": 15.175078643650115,
      "height": 13.513925750184024,
      "seed": 1594145808,
      "groupIds": [
        "u2YeWM_1DGS08E8xP1afa"
      ],
      "strokeSharpness": "round",
      "boundElementIds": []
    },
    {
      "type": "ellipse",
      "version": 2133,
      "versionNonce": 816679440,
      "isDeleted": false,
      "id": "3i2nxNHwwjKW83enW9Q8_",
      "fillStyle": "cross-hatch",
      "strokeWidth": 1,
      "strokeStyle": "solid",
      "roughness": 1,
      "opacity": 100,
      "angle": 0,
      "x": 983.7455576200874,
      "y": 467.97420897422575,
      "strokeColor": "#000000",
      "backgroundColor": "#000000",
      "width": 15.175078643650115,
      "height": 13.513925750184024,
      "seed": 230739184,
      "groupIds": [
        "u2YeWM_1DGS08E8xP1afa"
      ],
      "strokeSharpness": "round",
      "boundElementIds": []
    },
    {
      "type": "ellipse",
      "version": 2344,
      "versionNonce": 575921904,
      "isDeleted": false,
      "id": "51L5-FPfJYdlU-2YykPQa",
      "fillStyle": "cross-hatch",
      "strokeWidth": 1,
      "strokeStyle": "solid",
      "roughness": 1,
      "opacity": 100,
      "angle": 0,
      "x": 1022.4346917282986,
      "y": 530.9932537009224,
      "strokeColor": "#000000",
      "backgroundColor": "#000000",
      "width": 17.499041675769302,
      "height": 17.716882486131087,
      "seed": 1160952336,
      "groupIds": [
        "u2YeWM_1DGS08E8xP1afa"
      ],
      "strokeSharpness": "round",
      "boundElementIds": []
    },
    {
      "type": "ellipse",
      "version": 2409,
      "versionNonce": 1150404624,
      "isDeleted": false,
      "id": "VhcQYSL80zGDpfBoYeZVE",
      "fillStyle": "cross-hatch",
      "strokeWidth": 1,
      "strokeStyle": "solid",
      "roughness": 1,
      "opacity": 100,
      "angle": 0,
      "x": 997.8538268441129,
      "y": 590.4725779653572,
      "strokeColor": "#000000",
      "backgroundColor": "#000000",
      "width": 17.499041675769302,
      "height": 17.716882486131087,
      "seed": 1744416496,
      "groupIds": [
        "u2YeWM_1DGS08E8xP1afa"
      ],
      "strokeSharpness": "round",
      "boundElementIds": []
    },
    {
      "type": "ellipse",
      "version": 2428,
      "versionNonce": 1549435120,
      "isDeleted": false,
      "id": "8pElnbyS1SnJDZAbpcTMK",
      "fillStyle": "cross-hatch",
      "strokeWidth": 1,
      "strokeStyle": "solid",
      "roughness": 1,
      "opacity": 100,
      "angle": 0,
      "x": 947.2686169970688,
      "y": 629.752192698799,
      "strokeColor": "#000000",
      "backgroundColor": "#000000",
      "width": 17.499041675769302,
      "height": 17.716882486131087,
      "seed": 1894840336,
      "groupIds": [
        "u2YeWM_1DGS08E8xP1afa"
      ],
      "strokeSharpness": "round",
      "boundElementIds": []
    },
    {
      "type": "ellipse",
      "version": 2401,
      "versionNonce": 222184976,
      "isDeleted": false,
      "id": "mhQVxXkEomEYU3KMo0-RK",
      "fillStyle": "cross-hatch",
      "strokeWidth": 1,
      "strokeStyle": "solid",
      "roughness": 1,
      "opacity": 100,
      "angle": 0,
      "x": 875.0633808294234,
      "y": 642.9030397662193,
      "strokeColor": "#000000",
      "backgroundColor": "#000000",
      "width": 17.499041675769302,
      "height": 17.716882486131087,
      "seed": 214323440,
      "groupIds": [
        "u2YeWM_1DGS08E8xP1afa"
      ],
      "strokeSharpness": "round",
      "boundElementIds": []
    },
    {
      "type": "ellipse",
      "version": 2455,
      "versionNonce": 557638384,
      "isDeleted": false,
      "id": "gJIc0ti7h5i8diqMcLD6d",
      "fillStyle": "cross-hatch",
      "strokeWidth": 1,
      "strokeStyle": "solid",
      "roughness": 1,
      "opacity": 100,
      "angle": 0,
      "x": 805.348707584608,
      "y": 619.6992600544158,
      "strokeColor": "#000000",
      "backgroundColor": "#000000",
      "width": 17.499041675769302,
      "height": 17.716882486131087,
      "seed": 1178039824,
      "groupIds": [
        "u2YeWM_1DGS08E8xP1afa"
      ],
      "strokeSharpness": "round",
      "boundElementIds": []
    },
    {
      "type": "ellipse",
      "version": 2436,
      "versionNonce": 1202390032,
      "isDeleted": false,
      "id": "pWf3vBG-wDrR_fengGUc9",
      "fillStyle": "cross-hatch",
      "strokeWidth": 1,
      "strokeStyle": "solid",
      "roughness": 1,
      "opacity": 100,
      "angle": 0,
      "x": 758.338014379529,
      "y": 557.6017868749359,
      "strokeColor": "#000000",
      "backgroundColor": "#000000",
      "width": 17.499041675769302,
      "height": 17.716882486131087,
      "seed": 1940828912,
      "groupIds": [
        "u2YeWM_1DGS08E8xP1afa"
      ],
      "strokeSharpness": "round",
      "boundElementIds": []
    },
    {
      "type": "ellipse",
      "version": 2415,
      "versionNonce": 528680176,
      "isDeleted": false,
      "id": "gQU0H68vcwTIUXy8kj1aX",
      "fillStyle": "cross-hatch",
      "strokeWidth": 1,
      "strokeStyle": "solid",
      "roughness": 1,
      "opacity": 100,
      "angle": 0,
      "x": 751.6972162051596,
      "y": 494.9053976327372,
      "strokeColor": "#000000",
      "backgroundColor": "#000000",
      "width": 17.499041675769302,
      "height": 17.716882486131087,
      "seed": 1778267152,
      "groupIds": [
        "u2YeWM_1DGS08E8xP1afa"
      ],
      "strokeSharpness": "round",
      "boundElementIds": []
    },
    {
      "type": "ellipse",
      "version": 2422,
      "versionNonce": 1372586512,
      "isDeleted": false,
      "id": "Ua7vhk4KEKfetB7RE_dkS",
      "fillStyle": "cross-hatch",
      "strokeWidth": 1,
      "strokeStyle": "solid",
      "roughness": 1,
      "opacity": 100,
      "angle": 0,
      "x": 776.9803312614871,
      "y": 430.70539165560075,
      "strokeColor": "#000000",
      "backgroundColor": "#000000",
      "width": 17.499041675769302,
      "height": 17.716882486131087,
      "seed": 1664799984,
      "groupIds": [
        "u2YeWM_1DGS08E8xP1afa"
      ],
      "strokeSharpness": "round",
      "boundElementIds": []
    },
    {
      "type": "ellipse",
      "version": 2491,
      "versionNonce": 1958012656,
      "isDeleted": false,
      "id": "VJB3Cx4MNIJDzSNMSvmMw",
      "fillStyle": "cross-hatch",
      "strokeWidth": 1,
      "strokeStyle": "solid",
      "roughness": 1,
      "opacity": 100,
      "angle": 0,
      "x": 837.7808559248537,
      "y": 389.247325186967,
      "strokeColor": "#000000",
      "backgroundColor": "#000000",
      "width": 17.499041675769302,
      "height": 17.716882486131087,
      "seed": 574435856,
      "groupIds": [
        "u2YeWM_1DGS08E8xP1afa"
      ],
      "strokeSharpness": "round",
      "boundElementIds": []
    },
    {
      "type": "ellipse",
      "version": 2433,
      "versionNonce": 178602000,
      "isDeleted": false,
      "id": "FU0PFa-VgPXWd9f3dm636",
      "fillStyle": "cross-hatch",
      "strokeWidth": 1,
      "strokeStyle": "solid",
      "roughness": 1,
      "opacity": 100,
      "angle": 0,
      "x": 905.1293889500499,
      "y": 382.9502710908644,
      "strokeColor": "#000000",
      "backgroundColor": "#000000",
      "width": 17.499041675769302,
      "height": 17.716882486131087,
      "seed": 284342000,
      "groupIds": [
        "u2YeWM_1DGS08E8xP1afa"
      ],
      "strokeSharpness": "round",
      "boundElementIds": []
    },
    {
      "type": "ellipse",
      "version": 2422,
      "versionNonce": 1297778928,
      "isDeleted": false,
      "id": "oaEyaZOV2MT9LnnalVFAA",
      "fillStyle": "cross-hatch",
      "strokeWidth": 1,
      "strokeStyle": "solid",
      "roughness": 1,
      "opacity": 100,
      "angle": 0,
      "x": 975.9427779296619,
      "y": 415.9222874313204,
      "strokeColor": "#000000",
      "backgroundColor": "#000000",
      "width": 17.499041675769302,
      "height": 17.716882486131087,
      "seed": 904687632,
      "groupIds": [
        "u2YeWM_1DGS08E8xP1afa"
      ],
      "strokeSharpness": "round",
      "boundElementIds": []
    },
    {
      "type": "ellipse",
      "version": 2436,
      "versionNonce": 841137680,
      "isDeleted": false,
      "id": "9oWEgOa1mHQjmp7szZmKJ",
      "fillStyle": "cross-hatch",
      "strokeWidth": 1,
      "strokeStyle": "solid",
      "roughness": 1,
      "opacity": 100,
      "angle": 0,
      "x": 1015.3468153662724,
      "y": 466.659335153424,
      "strokeColor": "#000000",
      "backgroundColor": "#000000",
      "width": 17.499041675769302,
      "height": 17.716882486131087,
      "seed": 1096702192,
      "groupIds": [
        "u2YeWM_1DGS08E8xP1afa"
      ],
      "strokeSharpness": "round",
      "boundElementIds": []
    },
    {
      "type": "ellipse",
      "version": 2469,
      "versionNonce": 83618544,
      "isDeleted": false,
      "id": "FiPhzhSFSLH8gGfIzATGB",
      "fillStyle": "cross-hatch",
      "strokeWidth": 1,
      "strokeStyle": "solid",
      "roughness": 1,
      "opacity": 100,
      "angle": 0,
      "x": 1050.248438035579,
      "y": 551.8045324508939,
      "strokeColor": "#000000",
      "backgroundColor": "#000000",
      "width": 22.06050450560042,
      "height": 20.98561451860369,
      "seed": 1292103184,
      "groupIds": [
        "u2YeWM_1DGS08E8xP1afa"
      ],
      "strokeSharpness": "round",
      "boundElementIds": []
    },
    {
      "type": "ellipse",
      "version": 2550,
      "versionNonce": 1228962832,
      "isDeleted": false,
      "id": "Iwphzfi3d40DFnuVGOuDi",
      "fillStyle": "cross-hatch",
      "strokeWidth": 1,
      "strokeStyle": "solid",
      "roughness": 1,
      "opacity": 100,
      "angle": 0,
      "x": 1006.6171919802056,
      "y": 625.0325654157875,
      "strokeColor": "#000000",
      "backgroundColor": "#000000",
      "width": 22.06050450560042,
      "height": 20.98561451860369,
      "seed": 1745206000,
      "groupIds": [
        "u2YeWM_1DGS08E8xP1afa"
      ],
      "strokeSharpness": "round",
      "boundElementIds": []
    },
    {
      "type": "ellipse",
      "version": 2568,
      "versionNonce": 1176571120,
      "isDeleted": false,
      "id": "IakSPJB6Yw0-GUZrwYrJ6",
      "fillStyle": "cross-hatch",
      "strokeWidth": 1,
      "strokeStyle": "solid",
      "roughness": 1,
      "opacity": 100,
      "angle": 0,
      "x": 934.2221584687476,
      "y": 667.3552642284872,
      "strokeColor": "#000000",
      "backgroundColor": "#000000",
      "width": 22.06050450560042,
      "height": 20.98561451860369,
      "seed": 1350282256,
      "groupIds": [
        "u2YeWM_1DGS08E8xP1afa"
      ],
      "strokeSharpness": "round",
      "boundElementIds": []
    },
    {
      "type": "ellipse",
      "version": 2543,
      "versionNonce": 1911978512,
      "isDeleted": false,
      "id": "KNIZ0RH40x68j-dF_cL9G",
      "fillStyle": "cross-hatch",
      "strokeWidth": 1,
      "strokeStyle": "solid",
      "roughness": 1,
      "opacity": 100,
      "angle": 0,
      "x": 851.6982733753681,
      "y": 672.0854358083861,
      "strokeColor": "#000000",
      "backgroundColor": "#000000",
      "width": 22.06050450560042,
      "height": 20.98561451860369,
      "seed": 1198578928,
      "groupIds": [
        "u2YeWM_1DGS08E8xP1afa"
      ],
      "strokeSharpness": "round",
      "boundElementIds": []
    },
    {
      "type": "ellipse",
      "version": 2540,
      "versionNonce": 710012656,
      "isDeleted": false,
      "id": "BEa--63OEsEiPmBrxiU2P",
      "fillStyle": "cross-hatch",
      "strokeWidth": 1,
      "strokeStyle": "solid",
      "roughness": 1,
      "opacity": 100,
      "angle": 0,
      "x": 762.7233874514719,
      "y": 627.0507438384109,
      "strokeColor": "#000000",
      "backgroundColor": "#000000",
      "width": 22.06050450560042,
      "height": 20.98561451860369,
      "seed": 1246472720,
      "groupIds": [
        "u2YeWM_1DGS08E8xP1afa"
      ],
      "strokeSharpness": "round",
      "boundElementIds": []
    },
    {
      "type": "ellipse",
      "version": 2534,
      "versionNonce": 1329379344,
      "isDeleted": false,
      "id": "wEYvUD7VWQU0MBrgwUxSe",
      "fillStyle": "cross-hatch",
      "strokeWidth": 1,
      "strokeStyle": "solid",
      "roughness": 1,
      "opacity": 100,
      "angle": 0,
      "x": 717.1256300281689,
      "y": 544.7651598545135,
      "strokeColor": "#000000",
      "backgroundColor": "#000000",
      "width": 22.06050450560042,
      "height": 20.98561451860369,
      "seed": 287817456,
      "groupIds": [
        "u2YeWM_1DGS08E8xP1afa"
      ],
      "strokeSharpness": "round",
      "boundElementIds": []
    },
    {
      "type": "ellipse",
      "version": 2553,
      "versionNonce": 1511428336,
      "isDeleted": false,
      "id": "b7ed5KacG25_7C7YinjWy",
      "fillStyle": "cross-hatch",
      "strokeWidth": 1,
      "strokeStyle": "solid",
      "roughness": 1,
      "opacity": 100,
      "angle": 0,
      "x": 719.2724488727256,
      "y": 466.7162743565713,
      "strokeColor": "#000000",
      "backgroundColor": "#000000",
      "width": 22.06050450560042,
      "height": 20.98561451860369,
      "seed": 1164699664,
      "groupIds": [
        "u2YeWM_1DGS08E8xP1afa"
      ],
      "strokeSharpness": "round",
      "boundElementIds": []
    },
    {
      "type": "ellipse",
      "version": 2563,
      "versionNonce": 1695233552,
      "isDeleted": false,
      "id": "bms_gQom0bJrDiXaNP_3s",
      "fillStyle": "cross-hatch",
      "strokeWidth": 1,
      "strokeStyle": "solid",
      "roughness": 1,
      "opacity": 100,
      "angle": 0,
      "x": 771.0512731264645,
      "y": 389.3590947338867,
      "strokeColor": "#000000",
      "backgroundColor": "#000000",
      "width": 22.06050450560042,
      "height": 20.98561451860369,
      "seed": 95576304,
      "groupIds": [
        "u2YeWM_1DGS08E8xP1afa"
      ],
      "strokeSharpness": "round",
      "boundElementIds": []
    },
    {
      "type": "ellipse",
      "version": 2539,
      "versionNonce": 754381552,
      "isDeleted": false,
      "id": "770fbAPjx7X0PWTe5d18j",
      "fillStyle": "cross-hatch",
      "strokeWidth": 1,
      "strokeStyle": "solid",
      "roughness": 1,
      "opacity": 100,
      "angle": 0,
      "x": 845.7280924825342,
      "y": 351.9289496730101,
      "strokeColor": "#000000",
      "backgroundColor": "#000000",
      "width": 22.06050450560042,
      "height": 20.98561451860369,
      "seed": 768894480,
      "groupIds": [
        "u2YeWM_1DGS08E8xP1afa"
      ],
      "strokeSharpness": "round",
      "boundElementIds": []
    },
    {
      "type": "ellipse",
      "version": 2535,
      "versionNonce": 2019161104,
      "isDeleted": false,
      "id": "fx60ekvF-w4Q8ik7IDGtn",
      "fillStyle": "cross-hatch",
      "strokeWidth": 1,
      "strokeStyle": "solid",
      "roughness": 1,
      "opacity": 100,
      "angle": 0,
      "x": 926.5733255127576,
      "y": 352.67337703266236,
      "strokeColor": "#000000",
      "backgroundColor": "#000000",
      "width": 22.06050450560042,
      "height": 20.98561451860369,
      "seed": 345555696,
      "groupIds": [
        "u2YeWM_1DGS08E8xP1afa"
      ],
      "strokeSharpness": "round",
      "boundElementIds": []
    },
    {
      "type": "ellipse",
      "version": 2576,
      "versionNonce": 1232803056,
      "isDeleted": false,
      "id": "cpGyZWg6rNx_FnJI34Cb8",
      "fillStyle": "cross-hatch",
      "strokeWidth": 1,
      "strokeStyle": "solid",
      "roughness": 1,
      "opacity": 100,
      "angle": 0,
      "x": 1010.0187821533381,
      "y": 402.41926084814503,
      "strokeColor": "#000000",
      "backgroundColor": "#000000",
      "width": 22.06050450560042,
      "height": 20.98561451860369,
      "seed": 813507600,
      "groupIds": [
        "u2YeWM_1DGS08E8xP1afa"
      ],
      "strokeSharpness": "round",
      "boundElementIds": []
    },
    {
      "type": "ellipse",
      "version": 2523,
      "versionNonce": 1864430096,
      "isDeleted": false,
      "id": "fmRpn81YMeiUJjBva_vu_",
      "fillStyle": "cross-hatch",
      "strokeWidth": 1,
      "strokeStyle": "solid",
      "roughness": 1,
      "opacity": 100,
      "angle": 0,
      "x": 1052.8138654662307,
      "y": 479.92827834588473,
      "strokeColor": "#000000",
      "backgroundColor": "#000000",
      "width": 22.06050450560042,
      "height": 20.98561451860369,
      "seed": 2086855920,
      "groupIds": [
        "u2YeWM_1DGS08E8xP1afa"
      ],
      "strokeSharpness": "round",
      "boundElementIds": []
    },
    {
      "type": "line",
      "version": 2191,
      "versionNonce": 1160443632,
      "isDeleted": false,
      "id": "Ec1WjYj5u2P_cwKOuUL34",
      "fillStyle": "cross-hatch",
      "strokeWidth": 1,
      "strokeStyle": "solid",
      "roughness": 1,
      "opacity": 100,
      "angle": 0.06624602719969452,
      "x": 874.0121176537228,
      "y": 665.5628719610572,
      "strokeColor": "#000000",
      "backgroundColor": "#000000",
      "width": 55.801023761992305,
      "height": 72.18700335979086,
      "seed": 459153936,
      "groupIds": [
        "u2YeWM_1DGS08E8xP1afa"
      ],
      "strokeSharpness": "round",
      "boundElementIds": [],
      "startBinding": null,
      "endBinding": null,
      "points": [
        [
          0,
          -99.88129560928134
        ],
        [
          10.926360560744524,
          -166.84450627134547
        ],
        [
          15.742658657527343,
          -169.42430298849573
        ],
        [
          13.03802194165742,
          -142.49440143553096
        ],
        [
          15.790988935611647,
          -131.57376883588447
        ],
        [
          33.56723698637713,
          -134.42556769544555
        ],
        [
          39.63268688595348,
          -172.0682989690722
        ],
        [
          46.49558637392033,
          -171.39420670309724
        ],
        [
          41.56403915247497,
          -131.5112590267593
        ],
        [
          52.92165450227921,
          -135.56763880271058
        ],
        [
          55.801023761992305,
          -133.6298347198213
        ],
        [
          43.43776685666531,
          -123.11636060664193
        ],
        [
          33.75126381446742,
          -126.52230047682775
        ],
        [
          21.635234870109876,
          -122.76833302070015
        ],
        [
          13.406075597837614,
          -125.05416468952996
        ],
        [
          7.455874822923822,
          -105.05102576938609
        ],
        [
          0,
          -99.88129560928134
        ]
      ],
      "lastCommittedPoint": null,
      "startArrowhead": null,
      "endArrowhead": null
    }
  ]
}